easyclimate/__init__.py
easyclimate/backend.py
easyclimate/version.py
easyclimate/accessor/__init__.py
easyclimate/accessor/plot_accessor.py
easyclimate/accessor/top_accessor.py
easyclimate/core/__init__.py
easyclimate/core/datanode.py
easyclimate/core/diff.py
easyclimate/core/eddy.py
easyclimate/core/eof.py
easyclimate/core/extract.py
easyclimate/core/mk_test.py
easyclimate/core/normalized.py
easyclimate/core/read.py
easyclimate/core/spharm.py
easyclimate/core/stat.py
easyclimate/core/tutorial.py
easyclimate/core/units.py
easyclimate/core/utility.py
easyclimate/core/variability.py
easyclimate/core/windspharm.py
easyclimate/core/stats/__init__.py
easyclimate/core/stats/detrend_spatial.py
easyclimate/core/stats/monthstat.py
easyclimate/core/stats/seasonstat.py
easyclimate/core/stats/yearstat.py
easyclimate/field/__init__.py
easyclimate/field/air_sea_interaction/__init__.py
easyclimate/field/air_sea_interaction/index_amm.py
easyclimate/field/air_sea_interaction/index_atlantic_nino.py
easyclimate/field/air_sea_interaction/index_enso.py
easyclimate/field/air_sea_interaction/index_iobm.py
easyclimate/field/air_sea_interaction/index_iod.py
easyclimate/field/air_sea_interaction/index_pdo.py
easyclimate/field/boundary_layer/__init__.py
easyclimate/field/boundary_layer/aerobulk.py
easyclimate/field/detection/__init__.py
easyclimate/field/equatorial_wave/__init__.py
easyclimate/field/equatorial_wave/mjo.py
easyclimate/field/equatorial_wave/wk_spectra.py
easyclimate/field/heat_stress/__init__.py
easyclimate/field/heat_stress/humanindexmod_2020.py
easyclimate/field/land/__init__.py
easyclimate/field/monsoon/__init__.py
easyclimate/field/monsoon/bsiso.py
easyclimate/field/monsoon/index_npwi.py
easyclimate/field/ocean/__init__.py
easyclimate/field/ocean/mixlayer.py
easyclimate/field/ocean/oceanic_front.py
easyclimate/field/ocean/stability.py
easyclimate/field/ocean/thermal.py
easyclimate/field/satellite/__init__.py
easyclimate/field/satellite/image.py
easyclimate-2026.2.0.dist-info/licenses/LICENSE
easyclimate-2026.2.0.dist-info/METADATA
easyclimate-2026.2.0.dist-info/WHEEL
easyclimate-2026.2.0.dist-info/top_level.txt
easyclimate-2026.2.0.dist-info/RECORD
