Metadata-Version: 2.4
Name: easyclimate
Version: 2026.2.0
Summary: A line of code to analyze climate
Author-email: shenyulu <shenyulu2020@gmail.com>
License: BSD 3-Clause License
Project-URL: homepage, https://github.com/shenyulu/easyclimate
Project-URL: documentation, https://easyclimate.readthedocs.io/en/latest/
Project-URL: source, https://github.com/shenyulu/easyclimate
Project-URL: download, https://pypi.org/project/easyclimate/#files
Project-URL: tracker, https://github.com/shenyulu/easyclimate/issues
Keywords: climate,atmosphere,weather,meteorology
Classifier: Programming Language :: Python :: 3.10
Classifier: Programming Language :: Python :: 3.11
Classifier: Programming Language :: Python :: 3.12
Classifier: Programming Language :: Python :: 3.13
Classifier: Programming Language :: Python :: 3.14
Classifier: Programming Language :: Python :: 3 :: Only
Classifier: Topic :: Scientific/Engineering
Classifier: Operating System :: Microsoft :: Windows
Classifier: Operating System :: POSIX
Classifier: Operating System :: Unix
Requires-Python: >=3.10
License-File: LICENSE
Requires-Dist: numpy>=1.24.3
Requires-Dist: xarray>=2025.06.0
Requires-Dist: geocat.viz
Requires-Dist: cartopy>=0.25
Requires-Dist: xeofs>=3.0.0
Requires-Dist: matplotlib
Requires-Dist: pandas>=2.2.0
Requires-Dist: fast-barnes-py
Requires-Dist: oceans
Requires-Dist: intel-fortran-rt
Requires-Dist: dpcpp-cpp-rt
Requires-Dist: scipy>=1.8.0
Requires-Dist: statsmodels
Requires-Dist: geocat-comp
Requires-Dist: easyclimate-backend>=2025.12.1
Requires-Dist: easyclimate-rust>=2026.1.0
Requires-Dist: dask
Requires-Dist: pymannkendall
Requires-Dist: flox
Requires-Dist: xarray_regrid
Requires-Dist: gsw_xarray
Requires-Dist: pooch
Requires-Dist: zarr
Requires-Dist: metpy
Requires-Dist: tcpypi
Requires-Dist: netCDF4
Requires-Dist: seaborn
Requires-Dist: EMD-signal
Requires-Dist: pybarnes
Requires-Dist: rich
Dynamic: license-file
